dockwershell/.deprecated/03/__init__.py
dockwershell/.deprecated/03/core.py
dockwershell/.deprecated/03/image.py
dockwershell/.deprecated/03/path_to_mnt.py
dockwershell/.deprecated/__init__.py
dockwershell/.deprecated/dist/dockwershell-0.6-py3-none-any.whl
dockwershell/.deprecated/dist/dockwershell-0.6.tar.gz
dockwershell/.deprecated/unknown/__init__.py
dockwershell/.deprecated/unknown/docker.py
dockwershell/__init__.py
dockwershell/Dockerfile.foobar
dockwershell/pkg_docker/__init__.py
dockwershell/pkg_docker/mod_docker.py
dockwershell/pkg_docker/mod_docker_image.py
dockwershell-0.6.1.dist-info/licenses/LICENSE
dockwershell-0.6.1.dist-info/METADATA
dockwershell-0.6.1.dist-info/WHEEL
dockwershell-0.6.1.dist-info/RECORD
